<?xml version="1.0"?>
<CategoryConfiguration xmlns:xsd="http://www.w3.org/2001/XMLSchema" xmlns:xsi="http://www.w3.org/2001/XMLSchema-instance" xml:space="preserve">
  <Id>0aeadc4b-19f3-4d4e-a14b-efd72b3b7892</Id>
  <DisplayName>Monitoring</DisplayName>
  <Description>Assigned to objects used to monitor the Cisco Process Orchestrator service.</Description>
  <CreatedTime>2020-12-18T23:41:27.5911085Z</CreatedTime>
  <ModifiedTime>2020-12-18T23:41:27.5911085Z</ModifiedTime>
  <Version>3.5.13.28</Version>
  <SubCategories />
</CategoryConfiguration>